odoo/addons/website_sale_require_login/README.rst
odoo/addons/website_sale_require_login/__init__.py
odoo/addons/website_sale_require_login/__manifest__.py
odoo/addons/website_sale_require_login/controllers/__init__.py
odoo/addons/website_sale_require_login/controllers/main.py
odoo/addons/website_sale_require_login/demo/demo_assets.xml
odoo/addons/website_sale_require_login/i18n/ca.po
odoo/addons/website_sale_require_login/i18n/de.po
odoo/addons/website_sale_require_login/i18n/es.po
odoo/addons/website_sale_require_login/i18n/es_CL.po
odoo/addons/website_sale_require_login/i18n/fr.po
odoo/addons/website_sale_require_login/i18n/it.po
odoo/addons/website_sale_require_login/i18n/sl.po
odoo/addons/website_sale_require_login/i18n/website_sale_require_login.pot
odoo/addons/website_sale_require_login/readme/CONFIGURE.rst
odoo/addons/website_sale_require_login/readme/CONTRIBUTORS.rst
odoo/addons/website_sale_require_login/readme/DESCRIPTION.rst
odoo/addons/website_sale_require_login/readme/USAGE.rst
odoo/addons/website_sale_require_login/static/description/icon.png
odoo/addons/website_sale_require_login/static/description/index.html
odoo/addons/website_sale_require_login/static/src/js/website_sale_tour_buy_login.tour.js
odoo/addons/website_sale_require_login/tests/__init__.py
odoo/addons/website_sale_require_login/tests/test_checkout.py
odoo/addons/website_sale_require_login/views/website_sale.xml
odoo12_addon_website_sale_require_login-12.0.1.0.0.99.dev10.dist-info/METADATA
odoo12_addon_website_sale_require_login-12.0.1.0.0.99.dev10.dist-info/WHEEL
odoo12_addon_website_sale_require_login-12.0.1.0.0.99.dev10.dist-info/top_level.txt
odoo12_addon_website_sale_require_login-12.0.1.0.0.99.dev10.dist-info/RECORD
